hosker_rutil/__init__.py
hosker_rutil/primes.py
hosker_rutil/rust_utils.py
hosker_rutil/rust/hosker_primes/Cargo.toml
hosker_rutil/rust/hosker_primes/src/lib.rs
hosker_rutil-1.3.0.data/scripts/hosker-rutil-compile-rust
hosker_rutil-1.3.0.data/scripts/hosker-rutil-install-rust
hosker_rutil-1.3.0.dist-info/LICENSE
hosker_rutil-1.3.0.dist-info/METADATA
hosker_rutil-1.3.0.dist-info/WHEEL
hosker_rutil-1.3.0.dist-info/top_level.txt
hosker_rutil-1.3.0.dist-info/RECORD
