Metadata-Version: 2.1
Name: hosker-rutil
Version: 1.3.0
Summary: Rust utility functions
Home-page: https://github.com/tomhosker/hosker_rutil
Author: Tom Hosker
Author-email: tomdothosker@gmail.com
License: MIT
Platform: UNKNOWN
License-File: LICENSE
Requires-Dist: hosker-utils
Requires-Dist: sympy
